Workbook

Sheet INGRESOS
A1: RUBRO | B1: NOMBRE | C1: SSF | D1: DETALLE SECTORIAL | E1: PRESUPUESTO INICIAL | F1: ADICIONES | G1: REDUCCIONES | H1: CREDITOS | I1: CONTRACRED. | J1: LIBERACIONES | K1: APLAZAM. | L1: PRESUPUESTO DEFINITIVO | M1: RECONOCIM. | N1: RECAUDOS | O1: PORCENTAJE EJECUTADO | P1: NO AFORADO | Q1: SALDO POR EJECUTAR | R1: FUENTE DE RECURSO
A2: 1 | B2: Ingresos | C2: C | E2: 25022900237 | F2: 2696518395 | G2: 918409614 | H2: 0 | I2: 0 | J2: 0 | K2: 0 | L2: 26801009018 | M2: 1.014123e+10 | N2: 1.014123e+10 | O2: 37.84 % | P2: 30269649 | Q2: 1.665978e+10 | R2: 00
A3: 1.1 | B3: Ingresos corrientes | C3: C | E3: 25020700237 | F3: 23761460 | G3: 918409614 | H3: 0 | I3: 0 | J3: 0 | K3: 0 | L3: 24126052083 | M3: 1.0140777e+10 | N3: 1.0140777e+10 | O3: 42.03 % | P3: 30163256 | Q3: 1.3985275e+10 | R3: 00
A4: 1.1.01 | B4: Ingresos tributarios | C4: C | E4: 1058210195 | F4: 0 | G4: 0 | H4: 0 | I4: 0 | J4: 0 | K4: 0 | L4: 1058210195 | M4: 4.663506e+08 | N4: 4.663506e+08 | O4: 44.07 % | P4: 12252156 | Q4: 5.9185959e+08 | R4: 00
A5: 1.1.01.01 | B5: Impuestos directos | C5: C | E5: 219958465 | F5: 0 | G5: 0 | H5: 0 | I5: 0 | J5: 0 | K5: 0 | L5: 219958465 | M5: 207444500 | N5: 207444500 | O5: 94.31 % | P5: 12252156 | Q5: 12513965 | R5: 00
A6: 1.1.01.01.014 | B6: Sobretasa ambiental | C6: C | E6: 54319147 | F6: 0 | G6: 0 | H6: 0 | I6: 0 | J6: 0 | K6: 0 | L6: 54319147 | M6: 42503100 | N6: 42503100 | O6: 78.25 % | P6: 0 | Q6: 11816047 | R6: 00
A7: 1.1.01.01.014.01 | B7: Sobretasa ambiental - urbano | C7: C | E7: 25675660 | F7: 0 | G7: 0 | H7: 0 | I7: 0 | J7: 0 | K7: 0 | L7: 25675660 | M7: 16917800 | N7: 16917800 | O7: 65.89 % | P7: 0 | Q7: 8757860 | R7: 101.2
A8: 1.1.01.01.014.02 | B8: Sobretasa ambiental -rural | C8: C | E8: 28643487 | F8: 0 | G8: 0 | H8: 0 | I8: 0 | J8: 0 | K8: 0 | L8: 28643487 | M8: 25585300 | N8: 25585300 | O8: 89.32 % | P8: 0 | Q8: 3058187 | R8: 101.2
A9: 1.1.01.01.200 | B9: Impuesto predial unificado | C9: C | E9: 165639318 | F9: 0 | G9: 0 | H9: 0 | I9: 0 | J9: 0 | K9: 0 | L9: 165639318 | M9: 164941400 | N9: 164941400 | O9: 99.58 % | P9: 12252156 | Q9: 697918 | R9: 00
A10: 1.1.01.01.200.01 | B10: Impuesto predial unificado - urbano | C10: C | E10: 82490774 | F10: 0 | G10: 0 | H10: 0 | I10: 0 | J10: 0 | K10: 0 | L10: 82490774 | M10: 69540700 | N10: 69540700 | O10: 84.3 % | P10: 0 | Q10: 12950074 | R10: 100
A11: 1.1.01.01.200.02 | B11: Impuesto predial unificado - rural | C11: C | E11: 83148544 | F11: 0 | G11: 0 | H11: 0 | I11: 0 | J11: 0 | K11: 0 | L11: 83148544 | M11: 95400700 | N11: 95400700 | O11: 114.74 % | P11: 12252156 | Q11: -12252156 | R11: 100
A12: 1.1.01.02 | B12: Impuestos indirectos | C12: C | E12: 838251730 | F12: 0 | G12: 0 | H12: 0 | I12: 0 | J12: 0 | K12: 0 | L12: 838251730 | M12: 2.589061e+08 | N12: 2.589061e+08 | O12: 30.89 % | P12: 0 | Q12: 5.7934563e+08 | R12: 00
A13: 1.1.01.02.109 | B13: Sobretasa a la gasolina | C13: C | E13: 81106000 | F13: 0 | G13: 0 | H13: 0 | I13: 0 | J13: 0 | K13: 0 | L13: 81106000 | M13: 21346000 | N13: 21346000 | O13: 26.32 % | P13: 0 | Q13: 59760000 | R13: 100
... A55: 1.1.02.05.001.06.03 | B55: Servicios públicos - Aseo | C55: C | E55: 63134680 | F55: 0 | G55: 0 | H55: 0 | I55: 0 | J55: 0 | K55: 0 | L55: 63134680 | M55: 30188686 | N55: 30188686 | O55: 47.82 % | P55: 0 | Q55: 32945994 | R55: 104
A56: 1.1.02.05.001.06.04 | B56: Subsidio acueducto | C56: C | D56: 1 - IFSR Acueducto | E56: 177394675 | F56: 0 | G56: 0 | H56: 0 | I56: 0 | J56: 0 | K56: 0 | L56: 177394675 | M56: 73954524 | N56: 73954524 | O56: 41.69 % | P56: 0 | Q56: 1.0344015e+08 | R56: 292.1
A57: 1.1.02.05.001.06.05 | B57: Subsidio alcantarillado | C57: C | D57: 2 - IFSR Alcantarillado | E57: 78292899 | F57: 0 | G57: 0 | H57: 0 | I57: 0 | J57: 0 | K57: 0 | L57: 78292899 | M57: 32346900 | N57: 32346900 | O57: 41.32 % | P57: 0 | Q57: 45945999 | R57: 292.2
A58: 1.1.02.05.001.06.06 | B58: Subsidio aseo | C58: C | D58: 3 - IFSR Aseo | E58: 75428799 | F58: 0 | G58: 0 | H58: 0 | I58: 0 | J58: 0 | K58: 0 | L58: 75428799 | M58: 31541766 | N58: 31541766 | O58: 41.82 % | P58: 0 | Q58: 43887032 | R58: 292.3
A59: 1.1.02.05.001.07 | B59: Servicios financieros y servicios conexos; servicios inmobiliarios; y servicios de arrendamiento y leasing | C59: C | E59: 20922190 | F59: 0 | G59: 0 | H59: 0 | I59: 0 | J59: 0 | K59: 0 | L59: 20922190 | M59: 0 | N59: 0 | O59: 0 % | P59: 0 | Q59: 20922190 | R59: 00
A60: 1.1.02.05.001.07.01 | B60: Plaza de mercado | C60: C | E60: 18922190 | F60: 0 | G60: 0 | H60: 0 | I60: 0 | J60: 0 | K60: 0 | L60: 18922190 | M60: 0 | N60: 0 | O60: 0 % | P60: 0 | Q60: 18922190 | R60: 100
A61: 1.1.02.05.001.07.02 | B61: Arrendamientos complejo deportivo | C61: C | E61: 2000000 | F61: 0 | G61: 0 | H61: 0 | I61: 0 | J61: 0 | K61: 0 | L61: 2000000 | M61: 0 | N61: 0 | O61: 0 % | P61: 0 | Q61: 2000000 | R61: 100
A62: 1.1.02.06 | B62: Transferencias corrientes | C62: C | E62: 23075559295 | F62: 11506000 | G62: 918409614 | H62: 0 | I62: 0 | J62: 0 | K62: 0 | L62: 22168655681 | M62: 9.2801998e+09 | N62: 9.2801998e+09 | O62: 41.86 % | P62: 0 | Q62: 1.2888456e+10 | R62: 00
A63: 1.1.02.06.001 | B63: Sistema general de participaciones | C63: C | E63: 15017031481 | F63: 0 | G63: 918409614 | H63: 0 | I63: 0 | J63: 0 | K63: 0 | L63: 14098621867 | M63: 5034626147 | N63: 5034626147 | O63: 35.71 % | P63: 0 | Q63: 9063995720 | R63: 00
A64: 1.1.02.06.001.01 | B64: Participacion para educacion | C64: C | E64: 625208836 | F64: 0 | G64: 0 | H64: 0 | I64: 0 | J64: 0 | K64: 0 | L64: 625208836 | M64: 281284035 | N64: 281284035 | O64: 44.99 % | P64: 0 | Q64: 343924801 | R64: 00
A65: 1.1.02.06.001.01.03 | B65: Calidad | C65: C | E65: 625208836 | F65: 0 | G65: 0 | H65: 0 | I65: 0 | J65: 0 | K65: 0 | L65: 625208836 | M65: 281284035 | N65: 281284035 | O65: 44.99 % | P65: 0 | Q65: 343924801 | R65: 00
A66: 1.1.02.06.001.01.03.01 | B66: Calidad por matricula oficial | C66: C | E66: 174655711 | F66: 0 | G66: 0 | H66: 0 | I66: 0 | J66: 0 | K66: 0 | L66: 174655711 | M66: 62599200 | N66: 62599200 | O66: 35.84 % | P66: 0 | Q66: 112056511 | R66: 230
A67: 1.1.02.06.001.01.03.02 | B67: Calidad por gratuidad | C67: C | E67: 450553125 | F67: 0 | G67: 0 | H67: 0 | I67: 0 | J67: 0 | K67: 0 | L67: 450553125 | M67: 218684835 | N67: 218684835 | O67: 48.54 % | P67: 0 | Q67: 231868290 | R67: 231
A68: 1.1.02.06.001.02 | B68: Participacion para salud | C68: C | E68: 5575951282 | F68: 0 | G68: 0 | H68: 0 | I68: 0 | J68: 0 | K68: 0 | L68: 5575951282 | M68: 2258403875 | N68: 2258403875 | O68: 40.5 % | P68: 0 | Q68: 3317547407 | R68: 00
A69: 1.1.02.06.001.02.01 | B69: Regimen subsidiado | C69: C | D69: 9 - FLS Aseguramiento | E69: 5164858462 | F69: 0 | G69: 0 | H69: 0 | I69: 0 | J69: 0 | K69: 0 | L69: 5164858462 | M69: 2133097777 | N69: 2133097777 | O69: 41.3 % | P69: 0 | Q69: 3031760685 | R69: 260
A70: 1.1.02.06.001.02.02 | B70: Salud publica | C70: C | D70: 5 - FLS Salud publica | E70: 411092820 | F70: 0 | G70: 0 | H70: 0 | I70: 0 | J70: 0 | K70: 0 | L70: 411092820 | M70: 125306098 | N70: 125306098 | O70: 30.48 % | P70: 0 | Q70: 285786722 | R70: 261
A71: 1.1.02.06.001.03 | B71: Participacion para proposito general | C71: C | E71: 6949193063 | F71: 0 | G71: 918409614 | H71: 0 | I71: 0 | J71: 0 | K71: 0 | L71: 6030783449 | M71: 1892401862 | N71: 1892401862 | O71: 31.38 % | P71: 0 | Q71: 4138381587 | R71: 00
A72: 1.1.02.06.001.03.01 | B72: Deporte y recreacion | C72: C | E72: 177228932 | F72: 0 | G72: 59521148 | H72: 0 | I72: 0 | J72: 0 | K72: 0 | L72: 117707784 | M72: 37906412 | N72: 37906412 | O72: 32.2 % | P72: 0 | Q72: 79801372 | R72: 380
A73: 1.1.02.06.001.03.02 | B73: Cultura | C73: C | E73: 132921699 | F73: 0 | G73: 44640861 | H73: 0 | I73: 0 | J73: 0 | K73: 0 | L73: 88280838 | M73: 28429810 | N73: 28429810 | O73: 32.2 % | P73: 0 | Q73: 59851028 | R73: 400
A74: 1.1.02.06.001.03.03 | B74: Proposito general libre inversion | C74: C | E74: 3627336157 | F74: 0 | G74: 397266966 | H74: 0 | I74: 0 | J74: 0 | K74: 0 | L74: 3230069191 | M74: 1.011356e+09 | N74: 1.011356e+09 | O74: 31.31 % | P74: 0 | Q74: 2.2187132e+09 | R74: 420
A75: 1.1.02.06.001.03.04 | B75: Proposito general libre destinacion municipios categorias 4, 5 y 6 | C75: C | E75: 3011706275 | F75: 0 | G75: 416980639 | H75: 0 | I75: 0 | J75: 0 | K75: 0 | L75: 2594725636 | M75: 8.1470965e+08 | N75: 8.1470965e+08 | O75: 31.4 % | P75: 0 | Q75: 1.780016e+09 | R75: 360
A76: 1.1.02.06.001.04 | B76: Asignaciones especiales | C76: C | E76: 108490064 | F76: 0 | G76: 0 | H76: 0 | I76: 0 | J76: 0 | K76: 0 | L76: 108490064 | M76: 34188872 | N76: 34188872 | O76: 31.51 % | P76: 0 | Q76: 74301192 | R76: 00
A77: 1.1.02.06.001.04.01 | B77: Programas de alimentacion escolar | C77: C | E77: 108490064 | F77: 0 | G77: 0 | H77: 0 | I77: 0 | J77: 0 | K77: 0 | L77: 108490064 | M77: 34188872 | N77: 34188872 | O77: 31.51 % | P77: 0 | Q77: 74301192 | R77: 130
A78: 1.1.02.06.001.05 | B78: Agua potable y saneamiento basico | C78: C | E78: 1758188236 | F78: 0 | G78: 0 | H78: 0 | I78: 0 | J78: 0 | K78: 0 | L78: 1758188236 | M78: 568347503 | N78: 568347503 | O78: 32.33 % | P78: 0 | Q78: 1189840733 | R78: 290
A79: 1.1.02.06.003 | B79: Participaciones distintas del sgp | C79: C | E79: 33421973 | F79: 0 | G79: 0 | H79: 0 | I79: 0 | J79: 0 | K79: 0 | L79: 33421973 | M79: 6880698 | N79: 6880698 | O79: 20.59 % | P79: 0 | Q79: 26541275 | R79: 00
A80: 1.1.02.06.003.01 | B80: Participacion en impuestos | C80: C | E80: 33421973 | F80: 0 | G80: 0 | H80: 0 | I80: 0 | J80: 0 | K80: 0 | L80: 33421973 | M80: 6880698 | N80: 6880698 | O80: 20.59 % | P80: 0 | Q80: 26541275 | R80: 00
A81: 1.1.02.06.003.01.02 | B81: Participacion del impuesto sobre vehiculos automotores | C81: C | E81: 11330000 | F81: 0 | G81: 0 | H81: 0 | I81: 0 | J81: 0 | K81: 0 | L81: 11330000 | M81: 0 | N81: 0 | O81: 0 % | P81: 0 | Q81: 11330000 | R81: 100
A82: 1.1.02.06.003.01.08 | B82: Participacion del impuesto al deguello de ganado mayor en los terminos que lo defina la ordenanza | C82: C | E82: 22091973 | F82: 0 | G82: 0 | H82: 0 | I82: 0 | J82: 0 | K82: 0 | L82: 22091973 | M82: 6880698 | N82: 6880698 | O82: 31.15 % | P82: 0 | Q82: 15211275 | R82: 119
... A87: 1.1.02.06.009.01 | B87: Sistema general de seguridad social en salud | C87: C | E87: 8025105841 | F87: 0 | G87: 0 | H87: 0 | I87: 0 | J87: 0 | K87: 0 | L87: 8025105841 | M87: 4.238693e+09 | N87: 4.238693e+09 | O87: 52.82 % | P87: 0 | Q87: 3.7864129e+09 | R87: 00
A88: 1.1.02.06.009.01.06 | B88: Recursos adres - cofinanciacion upc regimen subsidiado | C88: C | D88: 9 - FLS Aseguramiento | E88: 7705754382 | F88: 0 | G88: 0 | H88: 0 | I88: 0 | J88: 0 | K88: 0 | L88: 7705754382 | M88: 4.0855619e+09 | N88: 4.0855619e+09 | O88: 53.02 % | P88: 0 | Q88: 3.6201925e+09 | R88: 600
A89: 1.1.02.06.009.01.09 | B89: Transferencia cajas de compensacion familiar - financiacion del regimen subsidiado en salud - ley 100 de 1993 | C89: C | D89: 9 - FLS Aseguramiento | E89: 3396564 | F89: 0 | G89: 0 | H89: 0 | I89: 0 | J89: 0 | K89: 0 | L89: 3396564 | M89: 1538907.9 | N89: 1538907.9 | O89: 45.31 % | P89: 0 | Q89: 1857656.1 | R89: 680
A90: 1.1.02.06.009.01.11 | B90: Aportes de unidades del gobierno general para el financiamiento del sgsss | C90: C | E90: 315954895 | F90: 0 | G90: 0 | H90: 0 | I90: 0 | J90: 0 | K90: 0 | L90: 315954895 | M90: 1.5159216e+08 | N90: 1.5159216e+08 | O90: 47.98 % | P90: 0 | Q90: 1.6436274e+08 | R90: 00
A91: 1.1.02.06.009.01.11.09 | B91: Recursos departamentales para aseguramiento del regimen subsidiado | C91: C | D91: 9 - FLS Aseguramiento | E91: 315954895 | F91: 0 | G91: 0 | H91: 0 | I91: 0 | J91: 0 | K91: 0 | L91: 315954895 | M91: 1.5159216e+08 | N91: 1.5159216e+08 | O91: 47.98 % | P91: 0 | Q91: 1.6436274e+08 | R91: 510
A92: 1.1.02.07 | B92: Participacion y derechos por monopolio | C92: C | E92: 142024213 | F92: 0 | G92: 0 | H92: 0 | I92: 0 | J92: 0 | K92: 0 | L92: 142024213 | M92: 33803130 | N92: 33803130 | O92: 23.8 % | P92: 0 | Q92: 1.0822108e+08 | R92: 00
A93: 1.1.02.07.001 | B93: Derechos por la explotacion juegos de suerte y azar | C93: C | E93: 142024213 | F93: 0 | G93: 0 | H93: 0 | I93: 0 | J93: 0 | K93: 0 | L93: 142024213 | M93: 33803130 | N93: 33803130 | O93: 23.8 % | P93: 0 | Q93: 1.0822108e+08 | R93: 00
A94: 1.1.02.07.001.05 | B94: Derechos por la explotacion juegos de suerte y azar de rifas | C94: C | E94: 142024213 | F94: 0 | G94: 0 | H94: 0 | I94: 0 | J94: 0 | K94: 0 | L94: 142024213 | M94: 33803130 | N94: 33803130 | O94: 23.8 % | P94: 0 | Q94: 1.0822108e+08 | R94: 00
A95: 1.1.02.07.001.05.01 | B95: Coljuegos SSF | C95: C | D95: 9 - FLS Aseguramiento | E95: 106032935 | F95: 0 | G95: 0 | H95: 0 | I95: 0 | J95: 0 | K95: 0 | L95: 106032935 | M95: 33803130 | N95: 33803130 | O95: 31.88 % | P95: 0 | Q95: 72229805 | R95: 630
A96: 1.1.02.07.001.05.02 | B96: Coljuegos CSF 25% | C96: C | D96: 9 - FLS Aseguramiento | E96: 35991278 | F96: 0 | G96: 0 | H96: 0 | I96: 0 | J96: 0 | K96: 0 | L96: 35991278 | M96: 0 | N96: 0 | O96: 0 % | P96: 0 | Q96: 35991278 | R96: 631
A97: 1.2 | B97: Recursos de capital | C97: C | E97: 2200000 | F97: 2672756935 | G97: 0 | H97: 0 | I97: 0 | J97: 0 | K97: 0 | L97: 2674956935 | M97: 452493.92 | N97: 452493.92 | O97: 0.02 % | P97: 106393.18 | Q97: 2.6745044e+09 | R97: 00
A98: 1.2.05 | B98: Rendimientos financieros | C98: C | E98: 2200000 | F98: 74817285 | G98: 0 | H98: 0 | I98: 0 | J98: 0 | K98: 0 | L98: 77017285 | M98: 452493.92 | N98: 452493.92 | O98: 0.59 % | P98: 106393.18 | Q98: 76564791 | R98: 00
A99: 1.2.05.02 | B99: Depositos | C99: C | E99: 2200000 | F99: 74817285 | G99: 0 | H99: 0 | I99: 0 | J99: 0 | K99: 0 | L99: 77017285 | M99: 452493.92 | N99: 452493.92 | O99: 0.59 % | P99: 106393.18 | Q99: 76564791 | R99: 00
A100: 1.2.05.02.01 | B100: Ingresos de Libre destinacion RF | C100: C | E100: 100000 | F100: 0 | G100: 0 | H100: 0 | I100: 0 | J100: 0 | K100: 0 | L100: 100000 | M100: 0 | N100: 0 | O100: 0 % | P100: 0 | Q100: 100000 | R100: 670
A101: 1.2.05.02.02 | B101: Sgp Educación Calidad Matricula Oficial RF | C101: C | E101: 100000 | F101: 0 | G101: 0 | H101: 0 | I101: 0 | J101: 0 | K101: 0 | L101: 100000 | M101: 0 | N101: 0 | O101: 0 % | P101: 0 | Q101: 100000 | R101: 240
A102: 1.2.05.02.03 | B102: Sgp Salud-Salud Pública Colectiva RF | C102: C | D102: 5 - FLS Salud publica | E102: 100000 | F102: 1246958 | G102: 0 | H102: 0 | I102: 0 | J102: 0 | K102: 0 | L102: 1346958 | M102: 0 | N102: 0 | O102: 0 % | P102: 0 | Q102: 1346958 | R102: 270
A103: 1.2.05.02.04 | B103: Sgp Agua Potable RF | C103: C | E103: 100000 | F103: 0 | G103: 0 | H103: 0 | I103: 0 | J103: 0 | K103: 0 | L103: 100000 | M103: 0 | N103: 0 | O103: 0 % | P103: 0 | Q103: 100000 | R103: 300
A104: 1.2.05.02.05 | B104: Sgp Deporte RF | C104: C | E104: 100000 | F104: 33859033 | G104: 0 | H104: 0 | I104: 0 | J104: 0 | K104: 0 | L104: 33959033 | M104: 0 | N104: 0 | O104: 0 % | P104: 0 | Q104: 33959033 | R104: 430.1
A105: 1.2.05.02.06 | B105: Sgp Cultura RF | C105: C | E105: 100000 | F105: 0 | G105: 0 | H105: 0 | I105: 0 | J105: 0 | K105: 0 | L105: 100000 | M105: 0 | N105: 0 | O105: 0 % | P105: 0 | Q105: 100000 | R105: 430.2
A106: 1.2.05.02.07 | B106: Sgp Libre Inversión RF | C106: C | E106: 100000 | F106: 0 | G106: 0 | H106: 0 | I106: 0 | J106: 0 | K106: 0 | L106: 100000 | M106: 0 | N106: 0 | O106: 0 % | P106: 0 | Q106: 100000 | R106: 430
A107: 1.2.05.02.08 | B107: Sgp Alimentación Escolar RF | C107: C | E107: 100000 | F107: 0 | G107: 0 | H107: 0 | I107: 0 | J107: 0 | K107: 0 | L107: 100000 | M107: 0 | N107: 0 | O107: 0 % | P107: 0 | Q107: 100000 | R107: 140
A108: 1.2.05.02.09 | B108: Coljuegos 25% RF | C108: C | D108: 9 - FLS Aseguramiento | E108: 100000 | F108: 0 | G108: 0 | H108: 0 | I108: 0 | J108: 0 | K108: 0 | L108: 100000 | M108: 0 | N108: 0 | O108: 0 % | P108: 0 | Q108: 100000 | R108: 631.2
A109: 1.2.05.02.10 | B109: Estampilla Proadulto RF | C109: C | E109: 100000 | F109: 0 | G109: 0 | H109: 0 | I109: 0 | J109: 0 | K109: 0 | L109: 100000 | M109: 67077 | N109: 67077 | O109: 67.08 % | P109: 0 | Q109: 32923 | R109: 151.2
A110: 1.2.05.02.11 | B110: Estampilla Procultura RF | C110: C | E110: 100000 | F110: 0 | G110: 0 | H110: 0 | I110: 0 | J110: 0 | K110: 0 | L110: 100000 | M110: 140 | N110: 140 | O110: 0.14 % | P110: 0 | Q110: 99860 | R110: 152.2
A111: 1.2.05.02.12 | B111: Estampilla Justicia Familiar RF | C111: C | E111: 100000 | F111: 0 | G111: 0 | H111: 0 | I111: 0 | J111: 0 | K111: 0 | L111: 100000 | M111: 1708 | N111: 1708 | O111: 1.71 % | P111: 0 | Q111: 98292 | R111: 153.2
A112: 1.2.05.02.13 | B112: Contrbucion de Seguridad RF | C112: C | E112: 100000 | F112: 0 | G112: 0 | H112: 0 | I112: 0 | J112: 0 | K112: 0 | L112: 100000 | M112: 7483 | N112: 7483 | O112: 7.48 % | P112: 0 | Q112: 92517 | R112: 676.2
A113: 1.2.05.02.14 | B113: Tasa del Deporte RF | C113: C | E113: 100000 | F113: 305089 | G113: 0 | H113: 0 | I113: 0 | J113: 0 | K113: 0 | L113: 405089 | M113: 0 | N113: 0 | O113: 0 % | P113: 0 | Q113: 405089 | R113: 117.2
A114: 1.2.05.02.15 | B114: RF Seguridad social gestor cultural | C114: C | E114: 100000 | F114: 0 | G114: 0 | H114: 0 | I114: 0 | J114: 0 | K114: 0 | L114: 100000 | M114: 5431.95 | N114: 5431.95 | O114: 5.43 % | P114: 0 | Q114: 94568.05 | R114: 152.4
A115: 1.2.05.02.16 | B115: Rend. Fcros. Otros gastos en salud | C115: C | D115: 9 - FLS Aseguramiento | E115: 100000 | F115: 0 | G115: 0 | H115: 0 | I115: 0 | J115: 0 | K115: 0 | L115: 100000 | M115: 66259.79 | N115: 66259.79 | O115: 66.26 % | P115: 0 | Q115: 33740.21 | R115: 670.9
A116: 1.2.05.02.17 | B116: REND. FCROS. SGP PRIMERA INFANCIA | C116: C | E116: 100000 | F116: 0 | G116: 0 | H116: 0 | I116: 0 | J116: 0 | K116: 0 | L116: 100000 | M116: 25360 | N116: 25360 | O116: 25.36 % | P116: 0 | Q116: 74640 | R116: 670.13
A117: 1.2.05.02.18 | B117: Rend. Fcros. Reg. Subsidiado | C117: C | D117: 9 - FLS Aseguramiento | E117: 100000 | F117: 0 | G117: 0 | H117: 0 | I117: 0 | J117: 0 | K117: 0 | L117: 100000 | M117: 0 | N117: 0 | O117: 0 % | P117: 0 | Q117: 100000 | R117: 670.22
A118: 1.2.05.02.19 | B118: Rend. Fcros. PG DESAHORRO FONPET | C118: C | E118: 100000 | F118: 0 | G118: 0 | H118: 0 | I118: 0 | J118: 0 | K118: 0 | L118: 100000 | M118: 344 | N118: 344 | O118: 0.34 % | P118: 0 | Q118: 99656 | R118: 670.23
A119: 1.2.05.02.20 | B119: Rend. Fcros. compra de areas estrategicas | C119: C | E119: 100000 | F119: 0 | G119: 0 | H119: 0 | I119: 0 | J119: 0 | K119: 0 | L119: 100000 | M119: 16597 | N119: 16597 | O119: 16.6 % | P119: 0 | Q119: 83403 | R119: 670.20
A120: 1.2.05.02.21 | B120: Rend. Fcros. Nomina Pensionados | C120: C | E120: 100000 | F120: 0 | G120: 0 | H120: 0 | I120: 0 | J120: 0 | K120: 0 | L120: 100000 | M120: 47252 | N120: 47252 | O120: 47.25 % | P120: 0 | Q120: 52748 | R120: 670.25
A121: 1.2.05.02.22 | B121: Rend. Fcros. libre inversion | C121: C | E121: 100000 | F121: 0 | G121: 0 | H121: 0 | I121: 0 | J121: 0 | K121: 0 | L121: 100000 | M121: 182207.18 | N121: 182207.18 | O121: 182.21 % | P121: 82207.18 | Q121: -82207.18 | R121: 670.24
A122: 1.2.05.02.23 | B122: RB RF REGIMEN SUBSIDIADO | C122: C | D122: 9 - FLS Aseguramiento | E122: 0 | F122: 68666 | G122: 0 | H122: 0 | I122: 0 | J122: 0 | K122: 0 | L122: 68666 | M122: 0 | N122: 0 | O122: 0 % | P122: 0 | Q122: 68666 | R122: 270.2
A123: 1.2.05.02.24 | B123: RENDIMIENTOS FINANCIEROS LIBRE DESTINACION RB | C123: C | E123: 0 | F123: 964878 | G123: 0 | H123: 0 | I123: 0 | J123: 0 | K123: 0 | L123: 964878 | M123: 586 | N123: 586 | O123: 0.06 % | P123: 0 | Q123: 964292 | R123: 670.1.1
A124: 1.2.05.02.25 | B124: REND. FCROS. SEGURIDAD SOCIAL DEL GESTOR RB | C124: C | E124: 0 | F124: 78760 | G124: 0 | H124: 0 | I124: 0 | J124: 0 | K124: 0 | L124: 78760 | M124: 2244 | N124: 2244 | O124: 2.85 % | P124: 0 | Q124: 76516 | R124: 670.10.1
A125: 1.2.05.02.26 | B125: REND. FCROS. OTROS GASTOS EN SALUD RB | C125: C | D125: 9 - FLS Aseguramiento | E125: 0 | F125: 21155 | G125: 0 | H125: 0 | I125: 0 | J125: 0 | K125: 0 | L125: 21155 | M125: 22 | N125: 22 | O125: 0.1 % | P125: 0 | Q125: 21133 | R125: 670.11.1
A126: 1.2.05.02.27 | B126: REND. FCROS.BANCO DE SEMILLA UMATA L.I RB | C126: C | E126: 0 | F126: 5073 | G126: 0 | H126: 0 | I126: 0 | J126: 0 | K126: 0 | L126: 5073 | M126: 29259 | N126: 29259 | O126: 576.76 % | P126: 24186 | Q126: -24186 | R126: 670.12.1
A127: 1.2.05.02.28 | B127: REND FCROS. SGP PRIMERA INFANCIA RB | C127: C | E127: 0 | F127: 44241 | G127: 0 | H127: 0 | I127: 0 | J127: 0 | K127: 0 | L127: 44241 | M127: 0 | N127: 0 | O127: 0 % | P127: 0 | Q127: 44241 | R127: 670.13.1
A128: 1.2.05.02.29 | B128: REND FCROS. DESEMBOLSO EMPRESTITO CIC RB | C128: C | E128: 0 | F128: 444819 | G128: 0 | H128: 0 | I128: 0 | J128: 0 | K128: 0 | L128: 444819 | M128: 0 | N128: 0 | O128: 0 % | P128: 0 | Q128: 444819 | R128: 670.17.1
A129: 1.2.05.02.30 | B129: RB REND FCROS. TASA AL DEPORTE RB | C129: C | E129: 0 | F129: 190945 | G129: 0 | H129: 0 | I129: 0 | J129: 0 | K129: 0 | L129: 190945 | M129: 420 | N129: 420 | O129: 0.22 % | P129: 0 | Q129: 190525 | R129: 670.19.1
A130: 1.2.05.02.31 | B130: REND. FCROS. COMPRA DE AREAS ESTRATEGICAS RB | C130: C | E130: 0 | F130: 66818 | G130: 0 | H130: 0 | I130: 0 | J130: 0 | K130: 0 | L130: 66818 | M130: 103 | N130: 103 | O130: 0.15 % | P130: 0 | Q130: 66715 | R130: 670.20.1
A131: 1.2.05.02.32 | B131: RB REND. FCROS COLJUEGOS 25% | C131: C | D131: 9 - FLS Aseguramiento | E131: 0 | F131: 40180 | G131: 0 | H131: 0 | I131: 0 | J131: 0 | K131: 0 | L131: 40180 | M131: 0 | N131: 0 | O131: 0 % | P131: 0 | Q131: 40180 | R131: 670.3.1
A132: 1.2.05.02.33 | B132: BALANCE SGP ALIMENTACION ESCOLAR RENDIMIENTOS FINANCIEROS | C132: C | E132: 0 | F132: 2944082 | G132: 0 | H132: 0 | I132: 0 | J132: 0 | K132: 0 | L132: 2944082 | M132: 0 | N132: 0 | O132: 0 % | P132: 0 | Q132: 2944082 | R132: 140.1
A133: 1.2.05.02.34 | B133: SGP EDUCACION RENDIMIENTOS FINANCIEROS RB | C133: C | E133: 0 | F133: 2528388 | G133: 0 | H133: 0 | I133: 0 | J133: 0 | K133: 0 | L133: 2528388 | M133: 0 | N133: 0 | O133: 0 % | P133: 0 | Q133: 2528388 | R133: 240.1
A134: 1.2.05.02.35 | B134: SGP APSB - RENDIMIENTOS FINANCIEROS RB | C134: C | E134: 0 | F134: 32008200 | G134: 0 | H134: 0 | I134: 0 | J134: 0 | K134: 0 | L134: 32008200 | M134: 0 | N134: 0 | O134: 0 % | P134: 0 | Q134: 32008200 | R134: 300.1
A135: 1.2.10 | B135: RECURSOS DEL BALANCE | C135: C | E135: 0 | F135: 2597939650 | G135: 0 | H135: 0 | I135: 0 | J135: 0 | K135: 0 | L135: 2597939650 | M135: 0 | N135: 0 | O135: 0 % | P135: 0 | Q135: 2597939650 | R135: 00
A136: 1.2.10.02 | B136: SUPERAVIT FISCAL | C136: C | E136: 0 | F136: 2597939650 | G136: 0 | H136: 0 | I136: 0 | J136: 0 | K136: 0 | L136: 2597939650 | M136: 0 | N136: 0 | O136: 0 % | P136: 0 | Q136: 2597939650 | R136: 00
A137: 1.2.10.02.01 | B137: Superavit fiscal | C137: C | E137: 0 | F137: 90719950 | G137: 0 | H137: 0 | I137: 0 | J137: 0 | K137: 0 | L137: 90719950 | M137: 0 | N137: 0 | O137: 0 % | P137: 0 | Q137: 90719950 | R137: 151.1
A138: 1.2.10.02.01 | B138: Superavit fiscal | C138: C | E138: 0 | F138: 99565927 | G138: 0 | H138: 0 | I138: 0 | J138: 0 | K138: 0 | L138: 99565927 | M138: 0 | N138: 0 | O138: 0 % | P138: 0 | Q138: 99565927 | R138: 510.1
A139: 1.2.10.02.02 | B139: Superavit fiscal | C139: C | E139: 0 | F139: 115911592 | G139: 0 | H139: 0 | I139: 0 | J139: 0 | K139: 0 | L139: 115911592 | M139: 0 | N139: 0 | O139: 0 % | P139: 0 | Q139: 115911592 | R139: 100.1
A140: 1.2.10.02.03 | B140: Superavit fiscal | C140: C | E140: 0 | F140: 4021970 | G140: 0 | H140: 0 | I140: 0 | J140: 0 | K140: 0 | L140: 4021970 | M140: 0 | N140: 0 | O140: 0 % | P140: 0 | Q140: 4021970 | R140: 101.2.1
A141: 1.2.10.02.04 | B141: Superavit fiscal | C141: C | E141: 0 | F141: 8887000 | G141: 0 | H141: 0 | I141: 0 | J141: 0 | K141: 0 | L141: 8887000 | M141: 0 | N141: 0 | O141: 0 % | P141: 0 | Q141: 8887000 | R141: 114.1
A142: 1.2.10.02.05 | B142: Superavit fiscal | C142: C | E142: 0 | F142: 618954316 | G142: 0 | H142: 0 | I142: 0 | J142: 0 | K142: 0 | L142: 618954316 | M142: 0 | N142: 0 | O142: 0 % | P142: 0 | Q142: 618954316 | R142: 115.3
A143: 1.2.10.02.06 | B143: Superavit fiscal | C143: C | E143: 0 | F143: 43937862 | G143: 0 | H143: 0 | I143: 0 | J143: 0 | K143: 0 | L143: 43937862 | M143: 0 | N143: 0 | O143: 0 % | P143: 0 | Q143: 43937862 | R143: 117.1
... A159: 1.2.10.02.23 | B159: Superavit fiscal | C159: C | E159: 0 | F159: 591872650 | G159: 0 | H159: 0 | I159: 0 | J159: 0 | K159: 0 | L159: 591872650 | M159: 0 | N159: 0 | O159: 0 % | P159: 0 | Q159: 591872650 | R159: 410
A160: 1.2.10.02.24 | B160: Superavit fiscal | C160: C | D160: 9 - FLS Aseguramiento | E160: 0 | F160: 10232114 | G160: 0 | H160: 0 | I160: 0 | J160: 0 | K160: 0 | L160: 10232114 | M160: 0 | N160: 0 | O160: 0 % | P160: 0 | Q160: 10232114 | R160: 630.1
...

Sheet EGRESOS
A2: UNIDAD EJECUTORA | B2: SECTOR | C2: SUBPROGRAMA | D2: PROGRAMA | E2: PRODUCTO | F2: NOMBRE DEL PRODUCTO | G2: BPIN | H2: NOMBRE DEL BPIN | I2: PRODUCTO DANE | J2: NOMBRE DEL PRODUCTO DANE | K2: ATRIBUTO | L2: NOMBRE DEL ATRIBUTO | M2: DEPENDENCIA | N2: RUBRO | O2: NOMBRE DEL RUBRO | P2: FUENTE DE RECURSO | Q2: NOMBRE DE FUENTE DE RECURSO | R2: PRESUPUESTO INICIAL | S2: ADICIONES | T2: REDUCCIONES | U2: CREDITOS | V2: CONTRACREDITOS | W2: LIBERACIONES | X2: APLAZAMIENTOS | Y2: PRESUPUESTO DEFINITIVO | Z2: DISPONIBILIDAD | AA2: REGISTRO | AB2: DEFINITIVAS | AC2: PAGOS | AD2: SALDO POR EJECUTAR | AE2: % EJECUTADO
A3: 1 - ADMINISTRACIÓN CENTRAL | B3: 00 - SIN SECTOR | C3: 00 | D3: 0000 | E3: 000000 | F3: SIN PRODUCTO | G3: 00 | H3: 00 | I3: 00 | J3: SIN PRODUCTO DANE | K3: 00 | L3: SIN ATRIBUTO | N3: 2 | O3: Gastos | P3: 00 | Q3: RECURSOS | R3: 9972660329 | S3: 2638356092 | T3: 895409614 | U3: 719815360 | V3: 719815360 | W3: 0 | X3: 0 | Y3: 11715606807 | Z3: 5.4998332e+09 | AA3: 5.1656976e+09 | AB3: 2.8674348e+09 | AC3: 2.8674348e+09 | AD3: 6.2157737e+09 | AE3: 46.94
A4: 1 - ADMINISTRACIÓN CENTRAL | B4: 00 - SIN SECTOR | C4: 00 | D4: 0000 | E4: 000000 | F4: SIN PRODUCTO | G4: 00 | H4: 00 | I4: 00 | J4: SIN PRODUCTO DANE | K4: 00 | L4: SIN ATRIBUTO | N4: 2.1 | O4: Funcionamiento | P4: 00 | Q4: RECURSOS | R4: 2399080536 | S4: 61287136 | T4: 152667595 | U4: 246798380 | V4: 246798380 | W4: 0 | X4: 0 | Y4: 2307700077 | Z4: 1.1658718e+09 | AA4: 1.1538985e+09 | AB4: 8.0967981e+08 | AC4: 8.0967981e+08 | AD4: 1.1418283e+09 | AE4: 50.52
A5: 1 - ADMINISTRACIÓN CENTRAL | B5: 00 - SIN SECTOR | C5: 00 | D5: 0000 | E5: 000000 | F5: SIN PRODUCTO | G5: 00 | H5: 00 | I5: 00 | J5: SIN PRODUCTO DANE | K5: 00 | L5: SIN ATRIBUTO | N5: 2.1.1 | O5: Gastos de personal | P5: 00 | Q5: RECURSOS | R5: 1044961427 | S5: 0 | T5: 0 | U5: 35333312 | V5: 15333312 | W5: 0 | X5: 0 | Y5: 1064961427 | Z5: 429657617 | AA5: 429657617 | AB5: 429657617 | AC5: 429657617 | AD5: 635303810 | AE5: 40.34
A6: 1 - ADMINISTRACIÓN CENTRAL | B6: 00 - SIN SECTOR | C6: 00 | D6: 0000 | E6: 000000 | F6: SIN PRODUCTO | G6: 00 | H6: 00 | I6: 00 | J6: SIN PRODUCTO DANE | K6: 00 | L6: SIN ATRIBUTO | N6: 2.1.1.01 | O6: Planta de personal permanente | P6: 00 | Q6: RECURSOS | R6: 1044961427 | S6: 0 | T6: 0 | U6: 35333312 | V6: 15333312 | W6: 0 | X6: 0 | Y6: 1064961427 | Z6: 429657617 | AA6: 429657617 | AB6: 429657617 | AC6: 429657617 | AD6: 635303810 | AE6: 40.34
A7: 1 - ADMINISTRACIÓN CENTRAL | B7: 00 - SIN SECTOR | C7: 00 | D7: 0000 | E7: 000000 | F7: SIN PRODUCTO | G7: 00 | H7: 00 | I7: 00 | J7: SIN PRODUCTO DANE | K7: 00 | L7: SIN ATRIBUTO | N7: 2.1.1.01.01 | O7: Factores constitutivos de salario | P7: 00 | Q7: RECURSOS | R7: 641724601 | S7: 0 | T7: 0 | U7: 0 | V7: 0 | W7: 0 | X7: 0 | Y7: 641724601 | Z7: 239489910 | AA7: 239489910 | AB7: 239489910 | AC7: 239489910 | AD7: 402234691 | AE7: 37.32
A8: 1 - ADMINISTRACIÓN CENTRAL | B8: 00 - SIN SECTOR | C8: 00 | D8: 0000 | E8: 000000 | F8: SIN PRODUCTO | G8: 00 | H8: 00 | I8: 00 | J8: SIN PRODUCTO DANE | K8: 00 | L8: SIN ATRIBUTO | N8: 2.1.1.01.01.001 | O8: Factores salariales comunes | P8: 00 | Q8: RECURSOS | R8: 641724601 | S8: 0 | T8: 0 | U8: 0 | V8: 0 | W8: 0 | X8: 0 | Y8: 641724601 | Z8: 239489910 | AA8: 239489910 | AB8: 239489910 | AC8: 239489910 | AD8: 402234691 | AE8: 37.32
A9: 1 - ADMINISTRACIÓN CENTRAL | B9: 00 - SIN SECTOR | C9: 00 | D9: 0000 | E9: 000000 | F9: SIN PRODUCTO | G9: 00 | H9: 00 | I9: 00 | J9: SIN PRODUCTO DANE | K9: 00 | L9: SIN ATRIBUTO | N9: 2.1.1.01.01.001.01 | O9: Sueldo basico | P9: 100 | Q9: INGRESOS CORRIENTES DE LIBRE DESTINACION EXCEPTO EL 42% DE LIBRE DESTINACIÓN DE PROPOSITO GENERAL DE MPIOS DE CATEGORIA | R9: 420525611 | S9: 0 | T9: 0 | U9: 0 | V9: 0 | W9: 0 | X9: 0 | Y9: 420525611 | Z9: 121199551 | AA9: 121199551 | AB9: 121199551 | AC9: 121199551 | AD9: 299326060 | AE9: 28.82
A10: 1 - ADMINISTRACIÓN CENTRAL | B10: 00 - SIN SECTOR | C10: 00 | D10: 0000 | E10: 000000 | F10: SIN PRODUCTO | G10: 00 | H10: 00 | I10: 00 | J10: SIN PRODUCTO DANE | K10: 00 | L10: SIN ATRIBUTO | N10: 2.1.1.01.01.001.01 | O10: Sueldo basico | P10: 360 | Q10: SGP PROPOSITO GENERAL 42 POR CIENTO RECURSOS LIBRE DESTINACION SGP PROPOSITO GENERAL MPIOS DE CATEGORIA 4 5 Y 6 SGP ONCE | R10: 84222946 | S10: 0 | T10: 0 | U10: 0 | V10: 0 | W10: 0 | X10: 0 | Y10: 84222946 | Z10: 81830446 | AA10: 81830446 | AB10: 81830446 | AC10: 81830446 | AD10: 2392500 | AE10: 97.16
A11: 1 - ADMINISTRACIÓN CENTRAL | B11: 00 - SIN SECTOR | C11: 00 | D11: 0000 | E11: 000000 | F11: SIN PRODUCTO | G11: 00 | H11: 00 | I11: 00 | J11: SIN PRODUCTO DANE | K11: 00 | L11: SIN ATRIBUTO | N11: 2.1.1.01.01.001.04 | O11: Subsidio de alimentacion | P11: 360 | Q11: SGP PROPOSITO GENERAL 42 POR CIENTO RECURSOS LIBRE DESTINACION SGP PROPOSITO GENERAL MPIOS DE CATEGORIA 4 5 Y 6 SGP ONCE | R11: 8891918 | S11: 0 | T11: 0 | U11: 0 | V11: 0 | W11: 0 | X11: 0 | Y11: 8891918 | Z11: 3637952 | AA11: 3637952 | AB11: 3637952 | AC11: 3637952 | AD11: 5253966 | AE11: 40.91
A12: 1 - ADMINISTRACIÓN CENTRAL | B12: 00 - SIN SECTOR | C12: 00 | D12: 0000 | E12: 000000 | F12: SIN PRODUCTO | G12: 00 | H12: 00 | I12: 00 | J12: SIN PRODUCTO DANE | K12: 00 | L12: SIN ATRIBUTO | N12: 2.1.1.01.01.001.05 | O12: Auxilio de transporte | P12: 360 | Q12: SGP PROPOSITO GENERAL 42 POR CIENTO RECURSOS LIBRE DESTINACION SGP PROPOSITO GENERAL MPIOS DE CATEGORIA 4 5 Y 6 SGP ONCE | R12: 17976000 | S12: 0 | T12: 0 | U12: 0 | V12: 0 | W12: 0 | X12: 0 | Y12: 17976000 | Z12: 8560565 | AA12: 8560565 | AB12: 8560565 | AC12: 8560565 | AD12: 9415435 | AE12: 47.62
A13: 1 - ADMINISTRACIÓN CENTRAL | B13: 00 - SIN SECTOR | C13: 00 | D13: 0000 | E13: 000000 | F13: SIN PRODUCTO | G13: 00 | H13: 00 | I13: 00 | J13: SIN PRODUCTO DANE | K13: 00 | L13: SIN ATRIBUTO | N13: 2.1.1.01.01.001.06 | O13: Prima de servicio | P13: 360 | Q13: SGP PROPOSITO GENERAL 42 POR CIENTO RECURSOS LIBRE DESTINACION SGP PROPOSITO GENERAL MPIOS DE CATEGORIA 4 5 Y 6 SGP ONCE | R13: 22109488 | S13: 0 | T13: 0 | U13: 0 | V13: 0 | W13: 0 | X13: 0 | Y13: 22109488 | Z13: 0 | AA13: 0 | AB13: 0 | AC13: 0 | AD13: 22109488 | AE13: 0
A14: 1 - ADMINISTRACIÓN CENTRAL | B14: 00 - SIN SECTOR | C14: 00 | D14: 0000 | E14: 000000 | F14: SIN PRODUCTO | G14: 00 | H14: 00 | I14: 00 | J14: SIN PRODUCTO DANE | K14: 00 | L14: SIN ATRIBUTO | N14: 2.1.1.01.01.001.07 | O14: Bonificacion por servicios prestados | P14: 360 | Q14: SGP PROPOSITO GENERAL 42 POR CIENTO RECURSOS LIBRE DESTINACION SGP PROPOSITO GENERAL MPIOS DE CATEGORIA 4 5 Y 6 SGP ONCE | R14: 16987259 | S14: 0 | T14: 0 | U14: 0 | V14: 0 | W14: 0 | X14: 0 | Y14: 16987259 | Z14: 10415841 | AA14: 10415841 | AB14: 10415841 | AC14: 10415841 | AD14: 6571418 | AE14: 61.32
... A730: R - SISTEMA GENERAL DE REGALIAS | B730: 00 - SIN SECTOR | C730: 00 | D730: 0000 | E730: 000000 | F730: SIN PRODUCTO | G730: 00 | H730: 00 | I730: 00 | J730: SIN PRODUCTO DANE | K730: 00 | L730: SIN ATRIBUTO | N730: 2.1.2.02.02.008 | O730: Servicios prestados a las empresas y servicios de produccion | P730: 00 | Q730: RECURSOS | R730: 0 | S730: 0 | T730: 0 | U730: 0 | V730: 0 | W730: 0 | X730: 0 | Y730: 0 | Z730: 45466666 | AA730: 45466666 | AB730: 17466666 | AC730: 17466666 | AD730: -45466666 | AE730: 0

Sheet CRUCE INFORMACION
A1: FUENTE DE RECURSO | B1: NOMBRE DE FUENTE DE RECURSO | C1: PRESUPUESTO DEFINITIVO | D1: PRESUPUESTO DEFINITIVO EJECUTADO | E1: DIFERENCIA | F1: Recaudo | G1: Registros | H1: Saldos no Comprometidos | I1: Constitución | J1: Reservas | K1: Pago | L1: Cuentas x Pagar | M1: Recurso en Bancos
A2: 100 | B2: INGRESOS CORRIENTES DE LIBRE DESTINACION EXCEPTO EL 42% DE LIBRE DESTINACIÓN DE PROPOSITO GENERAL DE MPIOS DE CATEGORIA | C2: =SUMIF(INGRESOS!$R:$R,A2,INGRESOS!$L:$L) | D2: =SUMIF(EGRESOS!$P:$P,A2,EGRESOS!$Y:$Y) | E2: =C2-D2 | F2: =SUMIF(INGRESOS!$R:$R,A2,INGRESOS!$N:$N) | G2: =SUMIF(EGRESOS!$P:$P,A2,EGRESOS!$AA:$AA) | H2: =F2-G2 | I2: =SUMIF(EGRESOS!$P:$P,A2,EGRESOS!$AB:$AB) | J2: =G2-I2 | K2: =SUMIF(EGRESOS!$P:$P,A2,EGRESOS!$AC:$AC) | L2: =I2-K2 | M2: =H2+J2+L2
A3: 360 | B3: SGP PROPOSITO GENERAL 42 POR CIENTO RECURSOS LIBRE DESTINACION SGP PROPOSITO GENERAL MPIOS DE CATEGORIA 4 5 Y 6 SGP ONCE | C3: =SUMIF(INGRESOS!$R:$R,A3,INGRESOS!$L:$L) | D3: =SUMIF(EGRESOS!$P:$P,A3,EGRESOS!$Y:$Y) | E3: =C3-D3 | F3: =SUMIF(INGRESOS!$R:$R,A3,INGRESOS!$N:$N) | G3: =SUMIF(EGRESOS!$P:$P,A3,EGRESOS!$AA:$AA) | H3: =F3-G3 | I3: =SUMIF(EGRESOS!$P:$P,A3,EGRESOS!$AB:$AB) | J3: =G3-I3 | K3: =SUMIF(EGRESOS!$P:$P,A3,EGRESOS!$AC:$AC) | L3: =I3-K3 | M3: =H3+J3+L3
A4: 138 | B4: MULTAS CODIGO POLICIA | C4: =SUMIF(INGRESOS!$R:$R,A4,INGRESOS!$L:$L) | D4: =SUMIF(EGRESOS!$P:$P,A4,EGRESOS!$Y:$Y) | E4: =C4-D4 | F4: =SUMIF(INGRESOS!$R:$R,A4,INGRESOS!$N:$N) | G4: =SUMIF(EGRESOS!$P:$P,A4,EGRESOS!$AA:$AA) | H4: =F4-G4 | I4: =SUMIF(EGRESOS!$P:$P,A4,EGRESOS!$AB:$AB) | J4: =G4-I4 | K4: =SUMIF(EGRESOS!$P:$P,A4,EGRESOS!$AC:$AC) | L4: =I4-K4 | M4: =H4+J4+L4
A5: 138.1 | B5: RB MULTAS CODIGO DE POLICIA | C5: =SUMIF(INGRESOS!$R:$R,A5,INGRESOS!$L:$L) | D5: =SUMIF(EGRESOS!$P:$P,A5,EGRESOS!$Y:$Y) | E5: =C5-D5 | F5: =SUMIF(INGRESOS!$R:$R,A5,INGRESOS!$N:$N) | G5: =SUMIF(EGRESOS!$P:$P,A5,EGRESOS!$AA:$AA) | H5: =F5-G5 | I5: =SUMIF(EGRESOS!$P:$P,A5,EGRESOS!$AB:$AB) | J5: =G5-I5 | K5: =SUMIF(EGRESOS!$P:$P,A5,EGRESOS!$AC:$AC) | L5: =I5-K5 | M5: =H5+J5+L5
A6: 101.2 | B6: SOBRETASA AMBIENTAL | C6: =SUMIF(INGRESOS!$R:$R,A6,INGRESOS!$L:$L) | D6: =SUMIF(EGRESOS!$P:$P,A6,EGRESOS!$Y:$Y) | E6: =C6-D6 | F6: =SUMIF(INGRESOS!$R:$R,A6,INGRESOS!$N:$N) | G6: =SUMIF(EGRESOS!$P:$P,A6,EGRESOS!$AA:$AA) | H6: =F6-G6 | I6: =SUMIF(EGRESOS!$P:$P,A6,EGRESOS!$AB:$AB) | J6: =G6-I6 | K6: =SUMIF(EGRESOS!$P:$P,A6,EGRESOS!$AC:$AC) | L6: =I6-K6 | M6: =H6+J6+L6
A7: 101.2.1 | B7: SOBRETASA AMBIENTAL RB | C7: =SUMIF(INGRESOS!$R:$R,A7,INGRESOS!$L:$L) | D7: =SUMIF(EGRESOS!$P:$P,A7,EGRESOS!$Y:$Y) | E7: =C7-D7 | F7: =SUMIF(INGRESOS!$R:$R,A7,INGRESOS!$N:$N) | G7: =SUMIF(EGRESOS!$P:$P,A7,EGRESOS!$AA:$AA) | H7: =F7-G7 | I7: =SUMIF(EGRESOS!$P:$P,A7,EGRESOS!$AB:$AB) | J7: =G7-I7 | K7: =SUMIF(EGRESOS!$P:$P,A7,EGRESOS!$AC:$AC) | L7: =I7-K7 | M7: =H7+J7+L7
A8: 114 | B8: SOBRETASA BOMBERIL | C8: =SUMIF(INGRESOS!$R:$R,A8,INGRESOS!$L:$L) | D8: =SUMIF(EGRESOS!$P:$P,A8,EGRESOS!$Y:$Y) | E8: =C8-D8 | F8: =SUMIF(INGRESOS!$R:$R,A8,INGRESOS!$N:$N) | G8: =SUMIF(EGRESOS!$P:$P,A8,EGRESOS!$AA:$AA) | H8: =F8-G8 | I8: =SUMIF(EGRESOS!$P:$P,A8,EGRESOS!$AB:$AB) | J8: =G8-I8 | K8: =SUMIF(EGRESOS!$P:$P,A8,EGRESOS!$AC:$AC) | L8: =I8-K8 | M8: =H8+J8+L8
A9: 114.1 | B9: SOBRETASA BOMBERIL RB | C9: =SUMIF(INGRESOS!$R:$R,A9,INGRESOS!$L:$L) | D9: =SUMIF(EGRESOS!$P:$P,A9,EGRESOS!$Y:$Y) | E9: =C9-D9 | F9: =SUMIF(INGRESOS!$R:$R,A9,INGRESOS!$N:$N) | G9: =SUMIF(EGRESOS!$P:$P,A9,EGRESOS!$AA:$AA) | H9: =F9-G9 | I9: =SUMIF(EGRESOS!$P:$P,A9,EGRESOS!$AB:$AB) | J9: =G9-I9 | K9: =SUMIF(EGRESOS!$P:$P,A9,EGRESOS!$AC:$AC) | L9: =I9-K9 | M9: =H9+J9+L9
A10: 152 | B10: Estampilla Procultura | C10: =SUMIF(INGRESOS!$R:$R,A10,INGRESOS!$L:$L) | D10: =SUMIF(EGRESOS!$P:$P,A10,EGRESOS!$Y:$Y) | E10: =C10-D10 | F10: =SUMIF(INGRESOS!$R:$R,A10,INGRESOS!$N:$N) | G10: =SUMIF(EGRESOS!$P:$P,A10,EGRESOS!$AA:$AA) | H10: =F10-G10 | I10: =SUMIF(EGRESOS!$P:$P,A10,EGRESOS!$AB:$AB) | J10: =G10-I10 | K10: =SUMIF(EGRESOS!$P:$P,A10,EGRESOS!$AC:$AC) | L10: =I10-K10 | M10: =H10+J10+L10
A11: 152.4 | B11: RF SEGURIDAD SOCIAL GESTOR CULTURAL | C11: =SUMIF(INGRESOS!$R:$R,A11,INGRESOS!$L:$L) | D11: =SUMIF(EGRESOS!$P:$P,A11,EGRESOS!$Y:$Y) | E11: =C11-D11 | F11: =SUMIF(INGRESOS!$R:$R,A11,INGRESOS!$N:$N) | G11: =SUMIF(EGRESOS!$P:$P,A11,EGRESOS!$AA:$AA) | H11: =F11-G11 | I11: =SUMIF(EGRESOS!$P:$P,A11,EGRESOS!$AB:$AB) | J11: =G11-I11 | K11: =SUMIF(EGRESOS!$P:$P,A11,EGRESOS!$AC:$AC) | L11: =I11-K11 | M11: =H11+J11+L11
A12: 152.1 | B12: RB ESTAMPILLA PROCULTURA | C12: =SUMIF(INGRESOS!$R:$R,A12,INGRESOS!$L:$L) | D12: =SUMIF(EGRESOS!$P:$P,A12,EGRESOS!$Y:$Y) | E12: =C12-D12 | F12: =SUMIF(INGRESOS!$R:$R,A12,INGRESOS!$N:$N) | G12: =SUMIF(EGRESOS!$P:$P,A12,EGRESOS!$AA:$AA) | H12: =F12-G12 | I12: =SUMIF(EGRESOS!$P:$P,A12,EGRESOS!$AB:$AB) | J12: =G12-I12 | K12: =SUMIF(EGRESOS!$P:$P,A12,EGRESOS!$AC:$AC) | L12: =I12-K12 | M12: =H12+J12+L12
A13: 670.10.1 | B13: REND. FCROS. SEGURIDAD SOCIAL DEL GESTOR | C13: =SUMIF(INGRESOS!$R:$R,A13,INGRESOS!$L:$L) | D13: =SUMIF(EGRESOS!$P:$P,A13,EGRESOS!$Y:$Y) | E13: =C13-D13 | F13: =SUMIF(INGRESOS!$R:$R,A13,INGRESOS!$N:$N) | G13: =SUMIF(EGRESOS!$P:$P,A13,EGRESOS!$AA:$AA) | H13: =F13-G13 | I13: =SUMIF(EGRESOS!$P:$P,A13,EGRESOS!$AB:$AB) | J13: =G13-I13 | K13: =SUMIF(EGRESOS!$P:$P,A13,EGRESOS!$AC:$AC) | L13: =I13-K13 | M13: =H13+J13+L13
... A95: 292.2.1 | B95: TRANSFERENCIA AAA ALCANTARILLADO RB | C95: =SUMIF(INGRESOS!$R:$R,A95,INGRESOS!$L:$L) | D95: =SUMIF(EGRESOS!$P:$P,A95,EGRESOS!$Y:$Y) | E95: =C95-D95 | F95: =SUMIF(INGRESOS!$R:$R,A95,INGRESOS!$N:$N) | G95: =SUMIF(EGRESOS!$P:$P,A95,EGRESOS!$AA:$AA) | H95: =F95-G95 | I95: =SUMIF(EGRESOS!$P:$P,A95,EGRESOS!$AB:$AB) | J95: =G95-I95 | K95: =SUMIF(EGRESOS!$P:$P,A95,EGRESOS!$AC:$AC) | L95: =I95-K95 | M95: =H95+J95+L95

Sheet INFORME RAPIDO
A1: CONCEPTO | B1: VALOR
A2: Recaudo hoja INGRESOS | B2: =INGRESOS!N2
A3: Suma recaudo hoja CRUCE INFORMACION | B3: =SUM('CRUCE INFORMACION'!F:F)
A4: Diferencia | B4: =B2-B3
A5: Resultado | B5: =IF(ABS(B4)<0.01,"Los datos coinciden","Los datos no coinciden, faltan productos")
A8: VALIDACION PRESUPUESTO DEFINITIVO | B8: VALOR
A9: Presupuesto Definitivo INGRESOS | B9: =INGRESOS!L2
A10: Suma Presupuesto Definitivo CRUCE | B10: =SUM('CRUCE INFORMACION'!C:C)
A11: Diferencia | B11: =B9-B10
A12: Resultado | B12: =IF(ABS(B11)<0.01,"Los datos coinciden","Los datos no coinciden, falta un producto")
